abc_exp_toolkit/__init__.py
abc_exp_toolkit/main.py
abc_exp_toolkit-0.0.2.dist-info/METADATA
abc_exp_toolkit-0.0.2.dist-info/WHEEL
abc_exp_toolkit-0.0.2.dist-info/licenses/LICENSE
abc_exp_toolkit-0.0.2.dist-info/RECORD
