Metadata-Version: 2.4
Name: abc_exp_toolkit
Version: 0.0.2
Summary: This is a library for summarizing the results of ab tests
Project-URL: Homepage, https://github.com/wellbel123/abc_exp_toolkit
Author-email: Nadia Beliaikina <belyaikinan@gmail.com>
License-File: LICENSE
Classifier: License :: OSI Approved :: MIT License
Classifier: Operating System :: OS Independent
Classifier: Programming Language :: Python :: 3
Requires-Python: >=3.09.0
Requires-Dist: numpy>=1.23.0
Requires-Dist: pandas>=1.5.0
Requires-Dist: scipy>=1.9.0
